README.txt
setup.py
src/ore/__init__.py
src/ore.workflow.egg-info/PKG-INFO
src/ore.workflow.egg-info/SOURCES.txt
src/ore.workflow.egg-info/dependency_links.txt
src/ore.workflow.egg-info/namespace_packages.txt
src/ore.workflow.egg-info/not-zip-safe
src/ore.workflow.egg-info/requires.txt
src/ore.workflow.egg-info/top_level.txt
src/ore/workflow/__init__.py
src/ore/workflow/interfaces.py
src/ore/workflow/tests.py
src/ore/workflow/workflow.py