Metadata-Version: 1.0
Name: ore.workflow
Version: 1.0.5
Summary: workflow engine for zope3
Home-page: UNKNOWN
Author: Zope 3 Community
Author-email: kapil.foss@gmail.com
License: BSD
Keywords: zope zope3
Platform: UNKNOWN
Classifier: Framework :: Zope3
